README.md
setup.py
src/vdk/plugin/test_utils/ingest_util_plugins.py
src/vdk/plugin/test_utils/util_funcs.py
src/vdk/plugin/test_utils/util_plugins.py
src/vdk_test_utils.egg-info/PKG-INFO
src/vdk_test_utils.egg-info/SOURCES.txt
src/vdk_test_utils.egg-info/dependency_links.txt
src/vdk_test_utils.egg-info/requires.txt
src/vdk_test_utils.egg-info/top_level.txt
tests/test_util_funcs.py
tests/test_vdk_test_utils.py