Metadata-Version: 2.1
Name: vdk-test-utils
Version: 0.2.1032157715
Summary: Provides utilities for testing Versatile Data Kit SDK plugins.
Home-page: https://github.com/vmware/versatile-data-kit
Classifier: Development Status :: 4 - Beta
Classifier: License :: OSI Approved :: Apache Software License
Classifier: Programming Language :: Python :: 3.7
Classifier: Programming Language :: Python :: 3.8
Classifier: Programming Language :: Python :: 3.9
Classifier: Programming Language :: Python :: 3.10
Classifier: Programming Language :: Python :: 3.11
Requires-Dist: vdk-core
